uart-rx/examples/rxleds/baudgen_rx.v
//-----------------------------------------------------------------------------
//-- Baudrate generator
//-- It generates a square signal, with a frequency for communicating at the given
//-- given baudrate
//-- The output is set to 1 only during one clock cycle. The rest of the time is 0
//-- Once enabled, the pulse is generated just in the middle of the period
//-- This is necessary for the implementation of the receptor
//--------------------------------------------------------------------------------
//-- (c) BQ. December 2015. written by Juan Gonzalez (obijuan)
//-----------------------------------------------------------------------------
//-- GPL license
//-----------------------------------------------------------------------------
`include "baudgen.vh"

//----------------------------------------------------------------------------------------
//-- baudgen module
//--
//-- INPUTS:
//--     -clk: System clock (12 MHZ in the iceStick board)
//--     -clk_ena: clock enable:
//--            1. Normal working: The squeare signal is generated
//--            0: stoped. Output always 0
//-- OUTPUTS:
//--     - clk_out: Output signal. Pulse width: 1 clock cycle. Output not registered
//--                It tells the uart_rx when to sample the next bit
//--                       __                                         __
//--   ____________________| |________________________________________| |_____________________
//--   |                  ->  <- 1 clock cycle   |
//--   <-------  Period ------------------------->
//--
//---------------------------------------------------------------------------------------
module baudgen_rx #(
         parameter BAUDRATE = `B115200  //-- Default baudrate
)(
         input wire rstn,         //-- Reset (active low)
         input wire clk,          //-- System clock
         input wire clk_ena,      //-- Clock enable
         output wire clk_out      //-- Bitrate Clock output
);

//-- Number of bits needed for storing the baudrate divisor
localparam N = $clog2(BAUDRATE);

//-- Value for generating the pulse in the middle of the period
localparam M2 = (BAUDRATE >> 1);

//-- Counter for implementing the divisor (it is a BAUDRATE module counter)
//-- (when BAUDRATE is reached, it start again from 0)
reg [N-1:0] divcounter = 0;

//-- Contador módulo M
always @(posedge clk)

  if (!rstn)
    divcounter <= 0;

  else if (clk_ena)
    //-- Normal working: counting. When the maximum count is reached, it starts from 0
    divcounter <= (divcounter == BAUDRATE - 1) ? 0 : divcounter + 1;
  else
    //-- Counter fixed to its maximum value
    //-- When it is resumed it start from 0
    divcounter <= BAUDRATE - 1;

//-- The output is 1 when the counter is in the middle of the period, if clk_ena is active
//-- It is 1 only for one system clock cycle
assign clk_out = (divcounter == M2) ? clk_ena : 0;


endmodule

uart-rx/uart_rx.v
//----------------------------------------------------------------------------
//-- Unidad de recepcion serie asincrona
//------------------------------------------
//-- (C) BQ. October 2015. Written by Juan Gonzalez (Obijuan)
//-- GPL license
//----------------------------------------------------------------------------
//-- Comprobado su funcionamiento a todas las velocidades estandares:
//-- 300, 600, 1200, 2400, 4800, 9600, 19200, 38400, 57600, 115200
//----------------------------------------------------------------------------
//-- Although this transmitter has been written from the scratch, it has been
//-- inspired by the one developed in the swapforth proyect by James Bowman
//--
//-- https://github.com/jamesbowman/swapforth
//--
//----------------------------------------------------------------------------

`default_nettype none

`include "baudgen.vh"

module uart_rx (input wire clk,         //-- Reloj del sistema
                input wire rstn,        //-- Reset
                input wire rx,          //-- Linea de recepcion serie
                output reg rcv,         //-- Indicar Dato disponible
                output reg [7:0] data); //-- Dato recibo

//-- Parametro: velocidad de recepcion
parameter BAUD = `B115200;

//-- Reloj para la recepcion
wire clk_baud;

//-- Linea de recepcion registrada
//-- Para cumplir reglas de diseño sincrono
reg rx_r;

//-- Microordenes
reg bauden;  //-- Activar señal de reloj de datos
reg clear;   //-- Poner a cero contador de bits
reg load;    //-- Cargar dato recibido


//-------------------------------------------------------------------
//--     RUTA DE DATOS
//-------------------------------------------------------------------

//-- Registrar la señal de recepcion de datos
//-- Para cumplir con las normas de diseño sincrono
always @(posedge clk)
  rx_r <= rx;

//-- Divisor para la generacion del reloj de llegada de datos
baudgen_rx #(BAUD)
  baudgen0 (
    .clk(clk),
    .clk_ena(bauden),
    .clk_out(clk_baud)
  );

//-- Contador de bits
reg [3:0] bitc;

always @(posedge clk)
  if (clear)
    bitc <= 4'd0;
  else if (clear == 0 && clk_baud == 1)
    bitc <= bitc + 1;


//-- Registro de desplazamiento para almacenar los bits recibidos
reg [9:0] raw_data;

always @(posedge clk)
  if (clk_baud == 1) begin
    raw_data = {rx_r, raw_data[9:1]};
  end

//-- Registro de datos. Almacenar el dato recibido
always @(posedge clk)
  if (rstn == 0)
    data <= 0;
  else if (load)
    data <= raw_data[8:1];

//-------------------------------------
//-- CONTROLADOR
//-------------------------------------
localparam IDLE = 2'd0;  //-- Estado de reposo
localparam RECV = 2'd1;  //-- Recibiendo datos
localparam LOAD = 2'd2;  //-- Almacenamiento del dato recibido
localparam DAV = 2'd3;   //-- Señalizar dato disponible

reg [1:0] state;
reg [1:0] next_state;

//-- Transition between states
always @(posedge clk)
  if (!rstn)
    state <= IDLE;
  else
    state <= next_state;

always @(*) begin

  //-- Default values
  next_state = state;      //-- Stay in the same state by default
  bauden = 0;
  clear = 0;
  load = 0;

  case(state)
    IDLE: begin
      clear = 1;
      rcv = 0;
      if (rx_r == 0)
        next_state = RECV;
    end

    RECV: begin
      bauden = 1;
      rcv = 0;
      if (bitc == 4'd10)
        next_state = LOAD;
    end

    LOAD: begin
      load = 1;
      rcv = 0;
      next_state = DAV;
    end

    DAV: begin
      rcv = 1;
      next_state = IDLE;
    end

    default:
      rcv = 0;

  endcase

end

endmodule

uart-rx/examples/rxleds.v
//----------------------------------------------------------------------------
//-- rxleds: Uart-rx example 1
//-- The 4-bits less significant of the character received are shown in the
//-- red leds of the icestick board
//----------------------------------------------------------------------------
//-- (C) BQ. December 2015. Written by Juan Gonzalez (Obijuan)
//-- GPL license
//----------------------------------------------------------------------------
`default_nettype none
`include "baudgen.vh"

//-- Top entity
module rxleds #(
         parameter BAUDRATE = `B115200
)(
         input wire clk,         //-- System clock
         input wire rx,          //-- Serial input
         output reg [3:0] leds   //-- Red leds
);

//-- Received character signal
wire rcv;

//-- Received data
wire [7:0] data;

//-- Reset signal
reg rstn = 0;

//-- Initialization
always @(posedge clk)
  rstn <= 1;

//-- Receiver unit instantation
uart_rx #(BAUDRATE)
  RX0 (.clk(clk),      //-- System clock
       .rstn(rstn),    //-- Reset (Active low)
       .rx(rx),        //-- Serial input
       .rcv(rcv),      //-- Character received notification (1)
       .data(data)     //-- Character received
      );

//-- Register the character received and show its 4 less significant leds
//-- in the icestick leds
always @(posedge clk)
    if (!rstn)
      leds <= 0;

    //-- When there is data available, capture it!
    else if (rcv == 1'b1)
      leds <= data[3:0];

endmodule

uart-rx/examples/rxleds/rxleds_tb.v
//-------------------------------------------------------------------
//-- rxleds_tb.v
//-- Testbench for the simulation of the rxleds.v
//-------------------------------------------------------------------
//-- (c) BQ December 2015. Written by Juan Gonzalez (Obijuan)
//-------------------------------------------------------------------
//-- GPL License
//-------------------------------------------------------------------
`timescale 100 ns / 10 ns

`include "baudgen.vh"


module rxleds_tb();

//-- Baudrate for the simulation
localparam BAUDRATE = `B115200;

//-- clock tics needed for sending one serial package
localparam SERIAL_PACK = (BAUDRATE * 10);

//-- Time between two characters
localparam WAIT = (BAUDRATE * 4);

//----------------------------------------
//-- Task for sending a character in serial
//----------------------------------------
  task send_char;
    input [7:0] char;
  begin
    rx <= 0;                   //-- Send the Start bit
    #BAUDRATE rx <= char[0];   //-- Bit 0
    #BAUDRATE rx <= char[1];   //-- Bit 1
    #BAUDRATE rx <= char[2];   //-- Bit 2
    #BAUDRATE rx <= char[3];   //-- Bit 3
    #BAUDRATE rx <= char[4];   //-- Bit 4
    #BAUDRATE rx <= char[5];   //-- Bit 5
    #BAUDRATE rx <= char[6];   //-- Bit 6
    #BAUDRATE rx <= char[7];   //-- Bit 7
    #BAUDRATE rx <= 1;         //-- stop bit
    #BAUDRATE rx <= 1;         //-- Wait until the bits stop is sent
  end
  endtask

//-- System clock
reg clk = 0;

//-- Wire connected to the rx port for transmiting to the receiver
reg rx = 1;

//-- For connecting the leds
wire [3:0] leds;

//-- Instantiate the entity to test
rxleds #(.BAUDRATE(BAUDRATE))
  dut(
    .clk(clk),
    .rx(rx),
    .leds(leds)
  );

//-- Clock generator
always
  # 0.5 clk <= ~clk;

initial begin

  //-- File where to store the simulation
  $dumpfile("rxleds_tb.vcd");
  $dumpvars(0, rxleds_tb);

  //-- Sent some data
  #BAUDRATE    send_char(8'h55);
  #WAIT        send_char("K");

  #(WAIT * 4) $display("END of the simulation");
  $finish;
end

endmodule

uart-rx/examples/rxleds/rxleds_tb.vcd
$date
	Mon Sep 19 17:11:57 2016
$end
$version
	Icarus Verilog
$end
$timescale
	10ns
$end
$scope module rxleds_tb $end
$var wire 4 ! leds [3:0] $end
$var reg 1 " clk $end
$var reg 1 # rx $end
$scope module dut $end
$var wire 1 " clk $end
$var wire 1 # rx $end
$var wire 1 $ rcv $end
$var wire 8 % data [7:0] $end
$var reg 4 & leds [3:0] $end
$var reg 1 ' rstn $end
$scope module RX0 $end
$var wire 1 " clk $end
$var wire 1 ' rstn $end
$var wire 1 # rx $end
$var wire 1 ( clk_baud $end
$var reg 1 ) bauden $end
$var reg 4 * bitc [3:0] $end
$var reg 1 + clear $end
$var reg 8 , data [7:0] $end
$var reg 1 - load $end
$var reg 2 . next_state [1:0] $end
$var reg 10 / raw_data [9:0] $end
$var reg 1 $ rcv $end
$var reg 1 0 rx_r $end
$var reg 2 1 state [1:0] $end
$scope module baudgen0 $end
$var wire 1 " clk $end
$var wire 1 ) clk_ena $end
$var wire 1 ' rstn $end
$var wire 1 ( clk_out $end
$var reg 7 2 divcounter [6:0] $end
$upscope $end
$upscope $end
$upscope $end
$scope task send_char $end
$var reg 8 3 char [7:0] $end
$upscope $end
$upscope $end
$enddefinitions $end
#0
$dumpvars
bx 3
b0 2
bx 1
x0
bx /
bx .
x-
bx ,
x+
bx *
x)
0(
0'
bx &
bx %
x$
1#
0"
bx !
$end
#5
0$
0-
1+
0)
b0 .
10
b0 %
b0 ,
b0 1
1'
b0 !
b0 &
1"
#10
0"
#15
1+
b0 *
b1100111 2
1"
#20
0"
#25
1"
#30
0"
#35
1"
#40
0"
#45
1"
#50
0"
#55
1"
#60
0"
#65
1"
#70
0"
#75
1"
#80
0"
#85
1"
#90
0"
#95
1"
#100
0"
#105
1"
#110
0"
#115
1"
#120
0"
#125
1"
#130
0"
#135
1"
#140
0"
#145
1"
#150
0"
#155
1"
#160
0"
#165
1"
#170
0"
#175
1"
#180
0"
#185
1"
#190
0"
#195
1"
#200
0"
#205
1"
#210
0"
#215
1"
#220
0"
#225
1"
#230
0"
#235
1"
#240
0"
#245
1"
#250
0"
#255
1"
#260
0"
#265
1"
#270
0"
#275
1"
#280
0"
#285
1"
#290
0"
#295
1"
#300
0"
#305
1"
#310
0"
#315
1"
#320
0"
#325
1"
#330
0"
#335
1"
#340
0"
#345
1"
#350
0"
#355
1"
#360
0"
#365
1"
#370
0"
#375
1"
#380
0"
#385
1"
#390
0"
#395
1"
#400
0"
#405
1"
#410
0"
#415
1"
#420
0"
#425
1"
#430
0"
#435
1"
#440
0"
#445
1"
#450
0"
#455
1"
#460
0"
#465
1"
#470
0"
#475
1"
#480
0"
#485
1"
#490
0"
#495
1"
#500
0"
#505
1"
#510
0"
#515
1"
#520
0"
#525
1"
#530
0"
#535
1"
#540
0"
#545
1"
#550
0"
#555
1"
#560
0"
#565
1"
#570
0"
#575
1"
#580
0"
#585
1"
#590
0"
#595
1"
#600
0"
#605
1"
#610
0"
#615
1"
#620
0"
#625
1"
#630
0"
#635
1"
#640
0"
#645
1"
#650
0"
#655
1"
#660
0"
#665
1"
#670
0"
#675
1"
#680
0"
#685
1"
#690
0"
#695
1"
#700
0"
#705
1"
#710
0"
#715
1"
#720
0"
#725
1"
#730
0"
#735
1"
#740
0"
#745
1"
#750
0"
#755
1"
#760
0"
#765
1"
#770
0"
#775
1"
#780
0"
#785
1"
#790
0"
#795
1"
#800
0"
#805
1"
#810
0"
#815
1"
#820
0"
#825
1"
#830
0"
#835
1"
#840
0"
#845
1"
#850
0"
#855
1"
#860
0"
#865
1"
#870
0"
#875
1"
#880
0"
#885
1"
#890
0"
#895
1"
#900
0"
#905
1"
#910
0"
#915
1"
#920
0"
#925
1"
#930
0"
#935
1"
#940
0"
#945
1"
#950
0"
#955
1"
#960
0"
#965
1"
#970
0"
#975
1"
#980
0"
#985
1"
#990
0"
#995
1"
#1000
0"
#1005
1"
#1010
0"
#1015
1"
#1020
0"
#1025
1"
#1030
0"
#1035
1"
#1040
0"
0#
b1010101 3
#1045
b1 .
1+
00
1"
#1050
0"
#1055
1)
0+
b1 1
1"
#1060
0"
#1065
b0 2
1"
#1070
0"
#1075
b1 2
1"
#1080
0"
#1085
b10 2
1"
#1090
0"
#1095
b11 2
1"
#1100
0"
#1105
b100 2
1"
#1110
0"
#1115
b101 2
1"
#1120
0"
#1125
b110 2
1"
#1130
0"
#1135
b111 2
1"
#1140
0"
#1145
b1000 2
1"
#1150
0"
#1155
b1001 2
1"
#1160
0"
#1165
b1010 2
1"
#1170
0"
#1175
b1011 2
1"
#1180
0"
#1185
b1100 2
1"
#1190
0"
#1195
b1101 2
1"
#1200
0"
#1205
b1110 2
1"
#1210
0"
#1215
b1111 2
1"
#1220
0"
#1225
b10000 2
1"
#1230
0"
#1235
b10001 2
1"
#1240
0"
#1245
b10010 2
1"
#1250
0"
#1255
b10011 2
1"
#1260
0"
#1265
b10100 2
1"
#1270
0"
#1275
b10101 2
1"
#1280
0"
#1285
b10110 2
1"
#1290
0"
#1295
b10111 2
1"
#1300
0"
#1305
b11000 2
1"
#1310
0"
#1315
b11001 2
1"
#1320
0"
#1325
b11010 2
1"
#1330
0"
#1335
b11011 2
1"
#1340
0"
#1345
b11100 2
1"
#1350
0"
#1355
b11101 2
1"
#1360
0"
#1365
b11110 2
1"
#1370
0"
#1375
b11111 2
1"
#1380
0"
#1385
b100000 2
1"
#1390
0"
#1395
b100001 2
1"
#1400
0"
#1405
b100010 2
1"
#1410
0"
#1415
b100011 2
1"
#1420
0"
#1425
b100100 2
1"
#1430
0"
#1435
b100101 2
1"
#1440
0"
#1445
b100110 2
1"
#1450
0"
#1455
b100111 2
1"
#1460
0"
#1465
b101000 2
1"
#1470
0"
#1475
b101001 2
1"
#1480
0"
#1485
b101010 2
1"
#1490
0"
#1495
b101011 2
1"
#1500
0"
#1505
b101100 2
1"
#1510
0"
#1515
b101101 2
1"
#1520
0"
#1525
b101110 2
1"
#1530
0"
#1535
b101111 2
1"
#1540
0"
#1545
b110000 2
1"
#1550
0"
#1555
b110001 2
1"
#1560
0"
#1565
b110010 2
1"
#1570
0"
#1575
b110011 2
1"
#1580
0"
#1585
1(
b110100 2
1"
#1590
0"
#1595
1)
0(
b0xxxxxxxxx /
b1 *
b110101 2
1"
#1600
0"
#1605
b110110 2
1"
#1610
0"
#1615
b110111 2
1"
#1620
0"
#1625
b111000 2
1"
#1630
0"
#1635
b111001 2
1"
#1640
0"
#1645
b111010 2
1"
#1650
0"
#1655
b111011 2
1"
#1660
0"
#1665
b111100 2
1"
#1670
0"
#1675
b111101 2
1"
#1680
0"
#1685
b111110 2
1"
#1690
0"
#1695
b111111 2
1"
#1700
0"
#1705
b1000000 2
1"
#1710
0"
#1715
b1000001 2
1"
#1720
0"
#1725
b1000010 2
1"
#1730
0"
#1735
b1000011 2
1"
#1740
0"
#1745
b1000100 2
1"
#1750
0"
#1755
b1000101 2
1"
#1760
0"
#1765
b1000110 2
1"
#1770
0"
#1775
b1000111 2
1"
#1780
0"
#1785
b1001000 2
1"
#1790
0"
#1795
b1001001 2
1"
#1800
0"
#1805
b1001010 2
1"
#1810
0"
#1815
b1001011 2
1"
#1820
0"
#1825
b1001100 2
1"
#1830
0"
#1835
b1001101 2
1"
#1840
0"
#1845
b1001110 2
1"
#1850
0"
#1855
b1001111 2
1"
#1860
0"
#1865
b1010000 2
1"
#1870
0"
#1875
b1010001 2
1"
#1880
0"
#1885
b1010010 2
1"
#1890
0"
#1895
b1010011 2
1"
#1900
0"
#1905
b1010100 2
1"
#1910
0"
#1915
b1010101 2
1"
#1920
0"
#1925
b1010110 2
1"
#1930
0"
#1935
b1010111 2
1"
#1940
0"
#1945
b1011000 2
1"
#1950
0"
#1955
b1011001 2
1"
#1960
0"
#1965
b1011010 2
1"
#1970
0"
#1975
b1011011 2
1"
#1980
0"
#1985
b1011100 2
1"
#1990
0"
#1995
b1011101 2
1"
#2000
0"
#2005
b1011110 2
1"
#2010
0"
#2015
b1011111 2
1"
#2020
0"
#2025
b1100000 2
1"
#2030
0"
#2035
b1100001 2
1"
#2040
0"
#2045
b1100010 2
1"
#2050
0"
#2055
b1100011 2
1"
#2060
0"
#2065
b1100100 2
1"
#2070
0"
#2075
b1100101 2
1"
#2080
0"
1#
#2085
1)
b1100110 2
10
1"
#2090
0"
#2095
b1100111 2
1"
#2100
0"
#2105
b0 2
1"
#2110
0"
#2115
b1 2
1"
#2120
0"
#2125
b10 2
1"
#2130
0"
#2135
b11 2
1"
#2140
0"
#2145
b100 2
1"
#2150
0"
#2155
b101 2
1"
#2160
0"
#2165
b110 2
1"
#2170
0"
#2175
b111 2
1"
#2180
0"
#2185
b1000 2
1"
#2190
0"
#2195
b1001 2
1"
#2200
0"
#2205
b1010 2
1"
#2210
0"
#2215
b1011 2
1"
#2220
0"
#2225
b1100 2
1"
#2230
0"
#2235
b1101 2
1"
#2240
0"
#2245
b1110 2
1"
#2250
0"
#2255
b1111 2
1"
#2260
0"
#2265
b10000 2
1"
#2270
0"
#2275
b10001 2
1"
#2280
0"
#2285
b10010 2
1"
#2290
0"
#2295
b10011 2
1"
#2300
0"
#2305
b10100 2
1"
#2310
0"
#2315
b10101 2
1"
#2320
0"
#2325
b10110 2
1"
#2330
0"
#2335
b10111 2
1"
#2340
0"
#2345
b11000 2
1"
#2350
0"
#2355
b11001 2
1"
#2360
0"
#2365
b11010 2
1"
#2370
0"
#2375
b11011 2
1"
#2380
0"
#2385
b11100 2
1"
#2390
0"
#2395
b11101 2
1"
#2400
0"
#2405
b11110 2
1"
#2410
0"
#2415
b11111 2
1"
#2420
0"
#2425
b100000 2
1"
#2430
0"
#2435
b100001 2
1"
#2440
0"
#2445
b100010 2
1"
#2450
0"
#2455
b100011 2
1"
#2460
0"
#2465
b100100 2
1"
#2470
0"
#2475
b100101 2
1"
#2480
0"
#2485
b100110 2
1"
#2490
0"
#2495
b100111 2
1"
#2500
0"
#2505
b101000 2
1"
#2510
0"
#2515
b101001 2
1"
#2520
0"
#2525
b101010 2
1"
#2530
0"
#2535
b101011 2
1"
#2540
0"
#2545
b101100 2
1"
#2550
0"
#2555
b101101 2
1"
#2560
0"
#2565
b101110 2
1"
#2570
0"
#2575
b101111 2
1"
#2580
0"
#2585
b110000 2
1"
#2590
0"
#2595
b110001 2
1"
#2600
0"
#2605
b110010 2
1"
#2610
0"
#2615
b110011 2
1"
#2620
0"
#2625
1(
b110100 2
1"
#2630
0"
#2635
1)
0(
b10xxxxxxxx /
b10 *
b110101 2
1"
#2640
0"
#2645
b110110 2
1"
#2650
0"
#2655
b110111 2
1"
#2660
0"
#2665
b111000 2
1"
#2670
0"
#2675
b111001 2
1"
#2680
0"
#2685
b111010 2
1"
#2690
0"
#2695
b111011 2
1"
#2700
0"
#2705
b111100 2
1"
#2710
0"
#2715
b111101 2
1"
#2720
0"
#2725
b111110 2
1"
#2730
0"
#2735
b111111 2
1"
#2740
0"
#2745
b1000000 2
1"
#2750
0"
#2755
b1000001 2
1"
#2760
0"
#2765
b1000010 2
1"
#2770
0"
#2775
b1000011 2
1"
#2780
0"
#2785
b1000100 2
1"
#2790
0"
#2795
b1000101 2
1"
#2800
0"
#2805
b1000110 2
1"
#2810
0"
#2815
b1000111 2
1"
#2820
0"
#2825
b1001000 2
1"
#2830
0"
#2835
b1001001 2
1"
#2840
0"
#2845
b1001010 2
1"
#2850
0"
#2855
b1001011 2
1"
#2860
0"
#2865
b1001100 2
1"
#2870
0"
#2875
b1001101 2
1"
#2880
0"
#2885
b1001110 2
1"
#2890
0"
#2895
b1001111 2
1"
#2900
0"
#2905
b1010000 2
1"
#2910
0"
#2915
b1010001 2
1"
#2920
0"
#2925
b1010010 2
1"
#2930
0"
#2935
b1010011 2
1"
#2940
0"
#2945
b1010100 2
1"
#2950
0"
#2955
b1010101 2
1"
#2960
0"
#2965
b1010110 2
1"
#2970
0"
#2975
b1010111 2
1"
#2980
0"
#2985
b1011000 2
1"
#2990
0"
#2995
b1011001 2
1"
#3000
0"
#3005
b1011010 2
1"
#3010
0"
#3015
b1011011 2
1"
#3020
0"
#3025
b1011100 2
1"
#3030
0"
#3035
b1011101 2
1"
#3040
0"
#3045
b1011110 2
1"
#3050
0"
#3055
b1011111 2
1"
#3060
0"
#3065
b1100000 2
1"
#3070
0"
#3075
b1100001 2
1"
#3080
0"
#3085
b1100010 2
1"
#3090
0"
#3095
b1100011 2
1"
#3100
0"
#3105
b1100100 2
1"
#3110
0"
#3115
b1100101 2
1"
#3120
0"
0#
#3125
1)
b1100110 2
00
1"
#3130
0"
#3135
b1100111 2
1"
#3140
0"
#3145
b0 2
1"
#3150
0"
#3155
b1 2
1"
#3160
0"
#3165
b10 2
1"
#3170
0"
#3175
b11 2
1"
#3180
0"
#3185
b100 2
1"
#3190
0"
#3195
b101 2
1"
#3200
0"
#3205
b110 2
1"
#3210
0"
#3215
b111 2
1"
#3220
0"
#3225
b1000 2
1"
#3230
0"
#3235
b1001 2
1"
#3240
0"
#3245
b1010 2
1"
#3250
0"
#3255
b1011 2
1"
#3260
0"
#3265
b1100 2
1"
#3270
0"
#3275
b1101 2
1"
#3280
0"
#3285
b1110 2
1"
#3290
0"
#3295
b1111 2
1"
#3300
0"
#3305
b10000 2
1"
#3310
0"
#3315
b10001 2
1"
#3320
0"
#3325
b10010 2
1"
#3330
0"
#3335
b10011 2
1"
#3340
0"
#3345
b10100 2
1"
#3350
0"
#3355
b10101 2
1"
#3360
0"
#3365
b10110 2
1"
#3370
0"
#3375
b10111 2
1"
#3380
0"
#3385
b11000 2
1"
#3390
0"
#3395
b11001 2
1"
#3400
0"
#3405
b11010 2
1"
#3410
0"
#3415
b11011 2
1"
#3420
0"
#3425
b11100 2
1"
#3430
0"
#3435
b11101 2
1"
#3440
0"
#3445
b11110 2
1"
#3450
0"
#3455
b11111 2
1"
#3460
0"
#3465
b100000 2
1"
#3470
0"
#3475
b100001 2
1"
#3480
0"
#3485
b100010 2
1"
#3490
0"
#3495
b100011 2
1"
#3500
0"
#3505
b100100 2
1"
#3510
0"
#3515
b100101 2
1"
#3520
0"
#3525
b100110 2
1"
#3530
0"
#3535
b100111 2
1"
#3540
0"
#3545
b101000 2
1"
#3550
0"
#3555
b101001 2
1"
#3560
0"
#3565
b101010 2
1"
#3570
0"
#3575
b101011 2
1"
#3580
0"
#3585
b101100 2
1"
#3590
0"
#3595
b101101 2
1"
#3600
0"
#3605
b101110 2
1"
#3610
0"
#3615
b101111 2
1"
#3620
0"
#3625
b110000 2
1"
#3630
0"
#3635
b110001 2
1"
#3640
0"
#3645
b110010 2
1"
#3650
0"
#3655
b110011 2
1"
#3660
0"
#3665
1(
b110100 2
1"
#3670
0"
#3675
1)
0(
b10xxxxxxx /
b11 *
b110101 2
1"
#3680
0"
#3685
b110110 2
1"
#3690
0"
#3695
b110111 2
1"
#3700
0"
#3705
b111000 2
1"
#3710
0"
#3715
b111001 2
1"
#3720
0"
#3725
b111010 2
1"
#3730
0"
#3735
b111011 2
1"
#3740
0"
#3745
b111100 2
1"
#3750
0"
#3755
b111101 2
1"
#3760
0"
#3765
b111110 2
1"
#3770
0"
#3775
b111111 2
1"
#3780
0"
#3785
b1000000 2
1"
#3790
0"
#3795
b1000001 2
1"
#3800
0"
#3805
b1000010 2
1"
#3810
0"
#3815
b1000011 2
1"
#3820
0"
#3825
b1000100 2
1"
#3830
0"
#3835
b1000101 2
1"
#3840
0"
#3845
b1000110 2
1"
#3850
0"
#3855
b1000111 2
1"
#3860
0"
#3865
b1001000 2
1"
#3870
0"
#3875
b1001001 2
1"
#3880
0"
#3885
b1001010 2
1"
#3890
0"
#3895
b1001011 2
1"
#3900
0"
#3905
b1001100 2
1"
#3910
0"
#3915
b1001101 2
1"
#3920
0"
#3925
b1001110 2
1"
#3930
0"
#3935
b1001111 2
1"
#3940
0"
#3945
b1010000 2
1"
#3950
0"
#3955
b1010001 2
1"
#3960
0"
#3965
b1010010 2
1"
#3970
0"
#3975
b1010011 2
1"
#3980
0"
#3985
b1010100 2
1"
#3990
0"
#3995
b1010101 2
1"
#4000
0"
#4005
b1010110 2
1"
#4010
0"
#4015
b1010111 2
1"
#4020
0"
#4025
b1011000 2
1"
#4030
0"
#4035
b1011001 2
1"
#4040
0"
#4045
b1011010 2
1"
#4050
0"
#4055
b1011011 2
1"
#4060
0"
#4065
b1011100 2
1"
#4070
0"
#4075
b1011101 2
1"
#4080
0"
#4085
b1011110 2
1"
#4090
0"
#4095
b1011111 2
1"
#4100
0"
#4105
b1100000 2
1"
#4110
0"
#4115
b1100001 2
1"
#4120
0"
#4125
b1100010 2
1"
#4130
0"
#4135
b1100011 2
1"
#4140
0"
#4145
b1100100 2
1"
#4150
0"
#4155
b1100101 2
1"
#4160
0"
1#
#4165
1)
b1100110 2
10
1"
#4170
0"
#4175
b1100111 2
1"
#4180
0"
#4185
b0 2
1"
#4190
0"
#4195
b1 2
1"
#4200
0"
#4205
b10 2
1"
#4210
0"
#4215
b11 2
1"
#4220
0"
#4225
b100 2
1"
#4230
0"
#4235
b101 2
1"
#4240
0"
#4245
b110 2
1"
#4250
0"
#4255
b111 2
1"
#4260
0"
#4265
b1000 2
1"
#4270
0"
#4275
b1001 2
1"
#4280
0"
#4285
b1010 2
1"
#4290
0"
#4295
b1011 2
1"
#4300
0"
#4305
b1100 2
1"
#4310
0"
#4315
b1101 2
1"
#4320
0"
#4325
b1110 2
1"
#4330
0"
#4335
b1111 2
1"
#4340
0"
#4345
b10000 2
1"
#4350
0"
#4355
b10001 2
1"
#4360
0"
#4365
b10010 2
1"
#4370
0"
#4375
b10011 2
1"
#4380
0"
#4385
b10100 2
1"
#4390
0"
#4395
b10101 2
1"
#4400
0"
#4405
b10110 2
1"
#4410
0"
#4415
b10111 2
1"
#4420
0"
#4425
b11000 2
1"
#4430
0"
#4435
b11001 2
1"
#4440
0"
#4445
b11010 2
1"
#4450
0"
#4455
b11011 2
1"
#4460
0"
#4465
b11100 2
1"
#4470
0"
#4475
b11101 2
1"
#4480
0"
#4485
b11110 2
1"
#4490
0"
#4495
b11111 2
1"
#4500
0"
#4505
b100000 2
1"
#4510
0"
#4515
b100001 2
1"
#4520
0"
#4525
b100010 2
1"
#4530
0"
#4535
b100011 2
1"
#4540
0"
#4545
b100100 2
1"
#4550
0"
#4555
b100101 2
1"
#4560
0"
#4565
b100110 2
1"
#4570
0"
#4575
b100111 2
1"
#4580
0"
#4585
b101000 2
1"
#4590
0"
#4595
b101001 2
1"
#4600
0"
#4605
b101010 2
1"
#4610
0"
#4615
b101011 2
1"
#4620
0"
#4625
b101100 2
1"
#4630
0"
#4635
b101101 2
1"
#4640
0"
#4645
b101110 2
1"
#4650
0"
#4655
b101111 2
1"
#4660
0"
#4665
b110000 2
1"
#4670
0"
#4675
b110001 2
1"
#4680
0"
#4685
b110010 2
1"
#4690
0"
#4695
b110011 2
1"
#4700
0"
#4705
1(
b110100 2
1"
#4710
0"
#4715
1)
0(
b1010xxxxxx /
b100 *
b110101 2
1"
#4720
0"
#4725
b110110 2
1"
#4730
0"
#4735
b110111 2
1"
#4740
0"
#4745
b111000 2
1"
#4750
0"
#4755
b111001 2
1"
#4760
0"
#4765
b111010 2
1"
#4770
0"
#4775
b111011 2
1"
#4780
0"
#4785
b111100 2
1"
#4790
0"
#4795
b111101 2
1"
#4800
0"
#4805
b111110 2
1"
#4810
0"
#4815
b111111 2
1"
#4820
0"
#4825
b1000000 2
1"
#4830
0"
#4835
b1000001 2
1"
#4840
0"
#4845
b1000010 2
1"
#4850
0"
#4855
b1000011 2
1"
#4860
0"
#4865
b1000100 2
1"
#4870
0"
#4875
b1000101 2
1"
#4880
0"
#4885
b1000110 2
1"
#4890
0"
#4895
b1000111 2
1"
#4900
0"
#4905
b1001000 2
1"
#4910
0"
#4915
b1001001 2
1"
#4920
0"
#4925
b1001010 2
1"
#4930
0"
#4935
b1001011 2
1"
#4940
0"
#4945
b1001100 2
1"
#4950
0"
#4955
b1001101 2
1"
#4960
0"
#4965
b1001110 2
1"
#4970
0"
#4975
b1001111 2
1"
#4980
0"
#4985
b1010000 2
1"
#4990
0"
#4995
b1010001 2
1"
#5000
0"
#5005
b1010010 2
1"
#5010
0"
#5015
b1010011 2
1"
#5020
0"
#5025
b1010100 2
1"
#5030
0"
#5035
b1010101 2
1"
#5040
0"
#5045
b1010110 2
1"
#5050
0"
#5055
b1010111 2
1"
#5060
0"
#5065
b1011000 2
1"
#5070
0"
#5075
b1011001 2
1"
#5080
0"
#5085
b1011010 2
1"
#5090
0"
#5095
b1011011 2
1"
#5100
0"
#5105
b1011100 2
1"
#5110
0"
#5115
b1011101 2
1"
#5120
0"
#5125
b1011110 2
1"
#5130
0"
#5135
b1011111 2
1"
#5140
0"
#5145
b1100000 2
1"
#5150
0"
#5155
b1100001 2
1"
#5160
0"
#5165
b1100010 2
1"
#5170
0"
#5175
b1100011 2
1"
#5180
0"
#5185
b1100100 2
1"
#5190
0"
#5195
b1100101 2
1"
#5200
0"
0#
#5205
1)
b1100110 2
00
1"
#5210
0"
#5215
b1100111 2
1"
#5220
0"
#5225
b0 2
1"
#5230
0"
#5235
b1 2
1"
#5240
0"
#5245
b10 2
1"
#5250
0"
#5255
b11 2
1"
#5260
0"
#5265
b100 2
1"
#5270
0"
#5275
b101 2
1"
#5280
0"
#5285
b110 2
1"
#5290
0"
#5295
b111 2
1"
#5300
0"
#5305
b1000 2
1"
#5310
0"
#5315
b1001 2
1"
#5320
0"
